{
  "surveys": [
    {
      "userId": "L0MdDBf1TTTgTLfTIUy8kBO0dUo2",
      "id": "1733782566879",
      "name": "Encuesta fideos",
      "questions": [
        {
          "question": "asdasdasd",
          "answerType": "text"
        },
        {
          "question": "aasfasf",
          "answerType": "text"
        },
        {
          "question": "adssda",
          "answerType": "text"
        }
      ]
    },
    {
      "userId": "L0MdDBf1TTTgTLfTIUy8kBO0dUo2",
      "id": "1733782584631",
      "name": "Encuesta porotos",
      "questions": [
        {
          "question": "asfasfafs",
          "answerType": "text"
        },
        {
          "question": "asdasf",
          "answerType": "text"
        }
      ]
    },
    {
      "userId": "L0MdDBf1TTTgTLfTIUy8kBO0dUo2",
      "id": "1733782602715",
      "name": "Encuesta Macarrones",
      "questions": [
        {
          "question": "asdasdsad",
          "answerType": "text"
        }
      ]
    },
    {
      "userId": "L0MdDBf1TTTgTLfTIUy8kBO0dUo2",
      "id": "1733782613296",
      "name": "Encuesta Harinas",
      "questions": [
        {
          "question": "asasasgasf",
          "answerType": "text"
        }
      ]
    },
    {
      "userId": "L0MdDBf1TTTgTLfTIUy8kBO0dUo2",
      "id": "1733782624567",
      "name": "Encuesta Aceites",
      "questions": [
        {
          "question": "asfsaasg",
          "answerType": "text"
        }
      ]
    },
    {
      "userId": "L0MdDBf1TTTgTLfTIUy8kBO0dUo2",
      "id": "1734143896021",
      "name": "encuesta manjarate",
      "questions": [
        {
          "question": "asdasfsaf",
          "answerType": "text"
        }
      ]
    },
    {
      "id": "1734145413091",
      "userId": "uZxWrEgqOgcUlbDgrP0j06RBJ2A2",
      "name": "encuesta testa",
      "questions": [
        {
          "question": "asdsafasf",
          "answerType": "text"
        }
      ]
    },
    {
      "id": 1734149752294,
      "userId": "uZxWrEgqOgcUlbDgrP0j06RBJ2A2",
      "name": "Encuesta Seria",
      "questions": [
        {
          "question": "Pregunta seria 1",
          "answerType": "text"
        },
        {
          "question": "Pregunta seria 2",
          "answerType": "text"
        },
        {
          "question": "Pregunta seria 3",
          "answerType": "text"
        },
        {
          "question": "Pregunta seria 4",
          "answerType": "text"
        }
      ]
    }
  ]
}